clustercheck.py
license
clustercheck-0.1.2.dist-info/entry_points.txt
clustercheck-0.1.2.dist-info/license
clustercheck-0.1.2.dist-info/WHEEL
clustercheck-0.1.2.dist-info/METADATA
clustercheck-0.1.2.dist-info/RECORD
